project1/.DS_Store
project1/__init__.py
project1/main.py
adnan_project1-0.1.0.dist-info/METADATA
adnan_project1-0.1.0.dist-info/WHEEL
adnan_project1-0.1.0.dist-info/RECORD
