Metadata-Version: 2.3
Name: adnan-project1
Version: 0.1.0
Summary: A Python project using Poetry for dependency management
Author: Adnan
Author-email: adnanmunir1160@gmail.com
Requires-Python: >=3.13
Classifier: Programming Language :: Python :: 3
Classifier: Programming Language :: Python :: 3.13
Requires-Dist: pytest (>=8.4.1,<9.0.0)
Requires-Dist: requests (>=2.32.4,<3.0.0)
